Metadata-Version: 1.1
Name: calculatorfromreplit
Version: 2.0.1
Summary: A very, VERY basic calculator
Home-page: UNKNOWN
Author: mahouka_magician
Author-email: mahouka_magician_depression@outlook.com
License: MIT
Keywords: calculator
Platform: UNKNOWN
Classifier: Development Status :: 5 - Production/Stable
Classifier: Intended Audience :: Education
Classifier: Operating System :: Microsoft :: Windows :: Windows 10
Classifier: License :: OSI Approved :: MIT License
Classifier: Programming Language :: Python :: 3
